partitura/__init__.py
partitura/directions.py
partitura/display.py
partitura/performance.py
partitura/score.py
partitura/assets/musicxml.xsd
partitura/assets/score_example.krn
partitura/assets/score_example.mei
partitura/assets/score_example.mid
partitura/assets/score_example.musicxml
partitura/io/__init__.py
partitura/io/exportaudio.py
partitura/io/exportkern.py
partitura/io/exportmatch.py
partitura/io/exportmei.py
partitura/io/exportmidi.py
partitura/io/exportmusicxml.py
partitura/io/exportparangonada.py
partitura/io/importdcml.py
partitura/io/importkern.py
partitura/io/importmatch.py
partitura/io/importmei.py
partitura/io/importmidi.py
partitura/io/importmusic21.py
partitura/io/importmusicxml.py
partitura/io/importnakamura.py
partitura/io/importparangonada.py
partitura/io/matchfile_base.py
partitura/io/matchfile_utils.py
partitura/io/matchlines_v0.py
partitura/io/matchlines_v1.py
partitura/io/musescore.py
partitura/musicanalysis/__init__.py
partitura/musicanalysis/key_identification.py
partitura/musicanalysis/meter.py
partitura/musicanalysis/note_array_to_score.py
partitura/musicanalysis/note_features.py
partitura/musicanalysis/performance_codec.py
partitura/musicanalysis/performance_features.py
partitura/musicanalysis/pitch_spelling.py
partitura/musicanalysis/tonal_tension.py
partitura/musicanalysis/voice_separation.py
partitura/utils/__init__.py
partitura/utils/fluidsynth.py
partitura/utils/generic.py
partitura/utils/globals.py
partitura/utils/misc.py
partitura/utils/music.py
partitura/utils/normalize.py
partitura/utils/synth.py
partitura-1.7.0.dist-info/licenses/LICENSE
partitura-1.7.0.dist-info/METADATA
partitura-1.7.0.dist-info/WHEEL
partitura-1.7.0.dist-info/top_level.txt
partitura-1.7.0.dist-info/RECORD
