Metadata-Version: 2.4
Name: partitura
Version: 1.7.0
Summary: A package for handling symbolic musical information
Home-page: https://github.com/CPJKU/partitura
Author: Maarten Grachten, Carlos Cancino-Chacón, Silvan Peter, Emmanouil Karystinaios, Francesco Foscarin, Thassilo Gadermaier, Patricia Hu
Author-email: partitura-users@googlegroups.com
License: Apache 2.0
Keywords: music notation musicxml midi
Classifier: License :: OSI Approved :: MIT License
Classifier: Programming Language :: Python
Classifier: Programming Language :: Python :: 3
Classifier: Programming Language :: Python :: Implementation :: CPython
Classifier: Programming Language :: Python :: Implementation :: PyPy
Requires-Python: >=3.7
License-File: LICENSE
Requires-Dist: numpy
Requires-Dist: scipy
Requires-Dist: lxml
Requires-Dist: lark-parser
Requires-Dist: xmlschema
Requires-Dist: mido
Dynamic: author
Dynamic: author-email
Dynamic: classifier
Dynamic: description
Dynamic: description-content-type
Dynamic: home-page
Dynamic: keywords
Dynamic: license
Dynamic: license-file
Dynamic: requires-dist
Dynamic: requires-python
Dynamic: summary
